acoustic_engine/__init__.py
acoustic_engine/config.py
acoustic_engine/engine.py
acoustic_engine/events.py
acoustic_engine/models.py
acoustic_engine/parallel_engine.py
acoustic_engine/profiles.py
acoustic_engine/runner.py
acoustic_engine/analysis/__init__.py
acoustic_engine/analysis/event_buffer.py
acoustic_engine/analysis/generator.py
acoustic_engine/analysis/matcher.py
acoustic_engine/analysis/windowed_matcher.py
acoustic_engine/input/__init__.py
acoustic_engine/input/listener.py
acoustic_engine/processing/__init__.py
acoustic_engine/processing/dsp.py
acoustic_engine/processing/filter.py
acoustic_engine/tester/__init__.py
acoustic_engine/tester/__main__.py
acoustic_engine/tester/display.py
acoustic_engine/tester/mixer.py
acoustic_engine/tester/runner.py
acoustic_engine/tuner/__init__.py
acoustic_engine/tuner/__main__.py
acoustic_engine/tuner/app.js
acoustic_engine/tuner/audio-engine.js
acoustic_engine/tuner/check_braces.py
acoustic_engine/tuner/index.html
acoustic_engine/tuner/styles.css
acoustic_engine/tuner/visualizer.js
acoustic_engine-1.0.0.dist-info/licenses/LICENSE
acoustic_engine-1.0.0.dist-info/METADATA
acoustic_engine-1.0.0.dist-info/WHEEL
acoustic_engine-1.0.0.dist-info/entry_points.txt
acoustic_engine-1.0.0.dist-info/top_level.txt
acoustic_engine-1.0.0.dist-info/RECORD
