Metadata-Version: 2.4
Name: acoustic-engine
Version: 1.0.0
Summary: Real-time acoustic alarm pattern detection engine
Author-email: h0tp-ftw <try-cycling-reverb@duck.com>
License: CC BY-NC 4.0
Project-URL: Homepage, https://github.com/h0tp-ftw/acoustic-engine
Project-URL: Documentation, https://github.com/h0tp-ftw/acoustic-engine#readme
Project-URL: Repository, https://github.com/h0tp-ftw/acoustic-engine
Project-URL: Issues, https://github.com/h0tp-ftw/acoustic-engine/issues
Keywords: audio,alarm,detection,fft,pattern-matching,iot,home-automation
Classifier: Development Status :: 4 - Beta
Classifier: Intended Audience :: Developers
Classifier: License :: Other/Proprietary License
Classifier: Operating System :: OS Independent
Classifier: Programming Language :: Python :: 3
Classifier: Programming Language :: Python :: 3.9
Classifier: Programming Language :: Python :: 3.10
Classifier: Programming Language :: Python :: 3.11
Classifier: Programming Language :: Python :: 3.12
Classifier: Topic :: Multimedia :: Sound/Audio :: Analysis
Classifier: Topic :: Home Automation
Requires-Python: >=3.9
License-File: LICENSE
Requires-Dist: numpy>=1.21.0
Requires-Dist: scipy>=1.7.0
Requires-Dist: PyAudio>=0.2.11
Requires-Dist: PyYAML>=6.0
Provides-Extra: dev
Requires-Dist: pytest>=7.0; extra == "dev"
Requires-Dist: pytest-cov>=4.0; extra == "dev"
Requires-Dist: black>=23.0; extra == "dev"
Requires-Dist: ruff>=0.1.0; extra == "dev"
Provides-Extra: audio
Requires-Dist: pydub>=0.25.0; extra == "audio"
Provides-Extra: tuner
Dynamic: license-file
